amazedb/__init__.py
amazedb/dbms.py
amazedb/group.py
amazedb-1.1.0.dist-info/LICENSE
amazedb-1.1.0.dist-info/METADATA
amazedb-1.1.0.dist-info/WHEEL
amazedb-1.1.0.dist-info/top_level.txt
amazedb-1.1.0.dist-info/RECORD
