Metadata-Version: 2.1
Name: amazedb
Version: 1.1.0
Summary: This is a light-weight, NoSQL, file-based database managemet system
Home-page: https://github.com/jalaj-k/amazedb
Author: Jalaj Kumar
Author-email: axiom.jalaj.28@gmail.com
License: MIT
Download-URL: https://github.com/jalaj-k/amazedb/archive/v1.1.0.tar.gz
Keywords: database,nosql,dbms
Platform: UNKNOWN
Classifier: Development Status :: 4 - Beta
Classifier: License :: OSI Approved :: MIT License
Classifier: Programming Language :: Python :: 3
Requires-Dist: colorama
Requires-Dist: cryptography
